recursive_decorator/__init__.py
recursive_decorator/decorator_adapter.py
recursive_decorator/recursive_decorator.py
recursive_decorator/transformer.py
recursive_decorator/utils.py
recursive_decorator-1.0.7.dist-info/METADATA
recursive_decorator-1.0.7.dist-info/RECORD
recursive_decorator-1.0.7.dist-info/WHEEL
recursive_decorator-1.0.7.dist-info/top_level.txt
