Metadata-Version: 2.1
Name: recursive-decorator
Version: 1.0.7
Summary: Decorator to apply given decorator recursively on functions
Home-page: https://github.com/ronen-y/recursive_decorator
Author: yakobu
Author-email: ronenya4321@gmail.com
License: MIT
Keywords: decorator recursive recursive_decorator recursive-decorator
Platform: UNKNOWN
Classifier: Development Status :: 3 - Alpha
Classifier: Natural Language :: English
Classifier: Programming Language :: Python :: 3.4
Classifier: Programming Language :: Python :: 3.5
Classifier: Programming Language :: Python :: 3.6
Classifier: Programming Language :: Python :: 3 :: Only
Classifier: Programming Language :: Python :: Implementation :: CPython
Classifier: Operating System :: POSIX
Classifier: Topic :: Software Development :: Pre-processors
Provides-Extra: dev
Requires-Dist: codetransformer
Requires-Dist: cached-property
Provides-Extra: dev
Requires-Dist: mock; extra == 'dev'
Requires-Dist: flake8; extra == 'dev'
Requires-Dist: pytest; extra == 'dev'
Requires-Dist: pytest-cov; extra == 'dev'
